{
  "query": "s%C6%A1n+t%C3%B9ng",
  "tracks": {
    "totalCount": 1000,
    "items": [
      {
        "data": {
          "uri": "spotify:track:6HGOxrNik4iPurqStawTFQ",
          "id": "6HGOxrNik4iPurqStawTFQ",
          "name": "MAKING MY WAY",
          "albumOfTrack": {
            "uri": "spotify:album:371NWHWKJxyUYwOywWpTal",
            "name": "MAKING MY WAY",
            "coverArt": {
              "sources": [
                {
                  "url": "https://i.scdn.co/image/ab67616d00001e020b303433c40b65a63dec0a04",
                  "width": 300,
                  "height": 300
                },
                {
                  "url": "https://i.scdn.co/image/ab67616d000048510b303433c40b65a63dec0a04",
                  "width": 64,
                  "height": 64
                },
                {
                  "url": "https://i.scdn.co/image/ab67616d0000b2730b303433c40b65a63dec0a04",
                  "width": 640,
                  "height": 640
                }
              ]
            },
            "id": "371NWHWKJxyUYwOywWpTal",
            "sharingInfo": {
              "shareUrl": "https://open.spotify.com/album/371NWHWKJxyUYwOywWpTal?si=uZnghUFTQd6DtLsO_mRUsA"
            }
          },
          "artists": {
            "items": [
              {
                "uri": "spotify:artist:5dfZ5uSmzR7VQK0udbAVpf",
                "profile": {
                  "name": "Sơn Tùng M-TP"
                }
              }
            ]
          },
          "contentRating": {
            "label": "NONE"
          },
          "duration": {
            "totalMilliseconds": 258006
          },
          "playability": {
            "playable": true
          }
        }
      },
      {
        "data": {
          "uri": "spotify:track:5fFLotKS1286huYIMQHqz7",
          "id": "5fFLotKS1286huYIMQHqz7",
          "name": "Muộn Rồi Mà Sao Còn",
          "albumOfTrack": {
            "uri": "spotify:album:33Iz5SghJnJ9iM0xIWCS3M",
            "name": "Muộn Rồi Mà Sao Còn",
            "coverArt": {
              "sources": [
                {
                  "url": "https://i.scdn.co/image/ab67616d00001e0229f906fe7a60df7777b02ee1",
                  "width": 300,
                  "height": 300
                },
                {
                  "url": "https://i.scdn.co/image/ab67616d0000485129f906fe7a60df7777b02ee1",
                  "width": 64,
                  "height": 64
                },
                {
                  "url": "https://i.scdn.co/image/ab67616d0000b27329f906fe7a60df7777b02ee1",
                  "width": 640,
                  "height": 640
                }
              ]
            },
            "id": "33Iz5SghJnJ9iM0xIWCS3M",
            "sharingInfo": {
              "shareUrl": "https://open.spotify.com/album/33Iz5SghJnJ9iM0xIWCS3M?si=CqKkhP9ZTaeXrsRCAjkLwA"
            }
          },
          "artists": {
            "items": [
              {
                "uri": "spotify:artist:5dfZ5uSmzR7VQK0udbAVpf",
                "profile": {
                  "name": "Sơn Tùng M-TP"
                }
              }
            ]
          },
          "contentRating": {
            "label": "NONE"
          },
          "duration": {
            "totalMilliseconds": 275905
          },
          "playability": {
            "playable": true
          }
        }
      },
      {
        "data": {
          "uri": "spotify:track:0f5yQttJS5nNxRAleF4kZO",
          "id": "0f5yQttJS5nNxRAleF4kZO",
          "name": "Hãy Trao Cho Anh",
          "albumOfTrack": {
            "uri": "spotify:album:2bPHnJXjR8q8eC84jCmNt7",
            "name": "Hãy Trao Cho Anh",
            "coverArt": {
              "sources": [
                {
                  "url": "https://i.scdn.co/image/ab67616d00001e020ac09baba508700ed0b5d4e3",
                  "width": 300,
                  "height": 300
                },
                {
                  "url": "https://i.scdn.co/image/ab67616d000048510ac09baba508700ed0b5d4e3",
                  "width": 64,
                  "height": 64
                },
                {
                  "url": "https://i.scdn.co/image/ab67616d0000b2730ac09baba508700ed0b5d4e3",
                  "width": 640,
                  "height": 640
                }
              ]
            },
            "id": "2bPHnJXjR8q8eC84jCmNt7",
            "sharingInfo": {
              "shareUrl": "https://open.spotify.com/album/2bPHnJXjR8q8eC84jCmNt7?si=8kaRNc3QSwyEfoJ5liqUFw"
            }
          },
          "artists": {
            "items": [
              {
                "uri": "spotify:artist:5dfZ5uSmzR7VQK0udbAVpf",
                "profile": {
                  "name": "Sơn Tùng M-TP"
                }
              },
              {
                "uri": "spotify:artist:7hJcb9fa4alzcOq3EaNPoG",
                "profile": {
                  "name": "Snoop Dogg"
                }
              }
            ]
          },
          "contentRating": {
            "label": "NONE"
          },
          "duration": {
            "totalMilliseconds": 245658
          },
          "playability": {
            "playable": true
          }
        }
      },
      {
        "data": {
          "uri": "spotify:track:17iGUekw5nFt5mIRJcUm3R",
          "id": "17iGUekw5nFt5mIRJcUm3R",
          "name": "Chúng Ta Của Hiện Tại",
          "albumOfTrack": {
            "uri": "spotify:album:6oT0WOEPWOxsa2Vmnkxwxa",
            "name": "Chúng Ta Của Hiện Tại",
            "coverArt": {
              "sources": [
                {
                  "url": "https://i.scdn.co/image/ab67616d00001e025888c34015bebbf123957f6d",
                  "width": 300,
                  "height": 300
                },
                {
                  "url": "https://i.scdn.co/image/ab67616d000048515888c34015bebbf123957f6d",
                  "width": 64,
                  "height": 64
                },
                {
                  "url": "https://i.scdn.co/image/ab67616d0000b2735888c34015bebbf123957f6d",
                  "width": 640,
                  "height": 640
                }
              ]
            },
            "id": "6oT0WOEPWOxsa2Vmnkxwxa",
            "sharingInfo": {
              "shareUrl": "https://open.spotify.com/album/6oT0WOEPWOxsa2Vmnkxwxa?si=3XohKyu-QIG_gZUrHBYRRQ"
            }
          },
          "artists": {
            "items": [
              {
                "uri": "spotify:artist:5dfZ5uSmzR7VQK0udbAVpf",
                "profile": {
                  "name": "Sơn Tùng M-TP"
                }
              }
            ]
          },
          "contentRating": {
            "label": "NONE"
          },
          "duration": {
            "totalMilliseconds": 301538
          },
          "playability": {
            "playable": true
          }
        }
      },
      {
        "data": {
          "uri": "spotify:track:3ZYrI2prWaAm1RbpCqZzlO",
          "id": "3ZYrI2prWaAm1RbpCqZzlO",
          "name": "CHẠY NGAY ĐI - Onionn Remix",
          "albumOfTrack": {
            "uri": "spotify:album:7aqlLOsEHnLv8XPBs05iOJ",
            "name": "CHẠY NGAY ĐI (Onionn Remix)",
            "coverArt": {
              "sources": [
                {
                  "url": "https://i.scdn.co/image/ab67616d00001e02754d0b74f5f7eb1f109114f3",
                  "width": 300,
                  "height": 300
                },
                {
                  "url": "https://i.scdn.co/image/ab67616d00004851754d0b74f5f7eb1f109114f3",
                  "width": 64,
                  "height": 64
                },
                {
                  "url": "https://i.scdn.co/image/ab67616d0000b273754d0b74f5f7eb1f109114f3",
                  "width": 640,
                  "height": 640
                }
              ]
            },
            "id": "7aqlLOsEHnLv8XPBs05iOJ",
            "sharingInfo": {
              "shareUrl": "https://open.spotify.com/album/7aqlLOsEHnLv8XPBs05iOJ?si=zspARd6yTs-QokvfKH5p-Q"
            }
          },
          "artists": {
            "items": [
              {
                "uri": "spotify:artist:5dfZ5uSmzR7VQK0udbAVpf",
                "profile": {
                  "name": "Sơn Tùng M-TP"
                }
              },
              {
                "uri": "spotify:artist:25M5YMbLCbYDSFPhQXYE8c",
                "profile": {
                  "name": "Onionn."
                }
              }
            ]
          },
          "contentRating": {
            "label": "NONE"
          },
          "duration": {
            "totalMilliseconds": 230400
          },
          "playability": {
            "playable": true
          }
        }
      },
      {
        "data": {
          "uri": "spotify:track:7hX5Of6NDiEaAR9zWsAeYY",
          "id": "7hX5Of6NDiEaAR9zWsAeYY",
          "name": "Khuôn Mặt Đáng Thương",
          "albumOfTrack": {
            "uri": "spotify:album:5hxm3ulOLVvjFdZNFO3n4M",
            "name": "m-tp M-TP",
            "coverArt": {
              "sources": [
                {
                  "url": "https://i.scdn.co/image/ab67616d00001e02af31997b23b7e6e65de1816b",
                  "width": 300,
                  "height": 300
                },
                {
                  "url": "https://i.scdn.co/image/ab67616d00004851af31997b23b7e6e65de1816b",
                  "width": 64,
                  "height": 64
                },
                {
                  "url": "https://i.scdn.co/image/ab67616d0000b273af31997b23b7e6e65de1816b",
                  "width": 640,
                  "height": 640
                }
              ]
            },
            "id": "5hxm3ulOLVvjFdZNFO3n4M",
            "sharingInfo": {
              "shareUrl": "https://open.spotify.com/album/5hxm3ulOLVvjFdZNFO3n4M?si=DXBomR0sTpKLYUwjgs9kzQ"
            }
          },
          "artists": {
            "items": [
              {
                "uri": "spotify:artist:5dfZ5uSmzR7VQK0udbAVpf",
                "profile": {
                  "name": "Sơn Tùng M-TP"
                }
              }
            ]
          },
          "contentRating": {
            "label": "NONE"
          },
          "duration": {
            "totalMilliseconds": 257451
          },
          "playability": {
            "playable": true
          }
        }
      }
    ],
    "pagingInfo": {
      "nextOffset": 6,
      "limit": 6
    }
  }
}